Workbook
Name m.a: 'Lista de composição de preço'!$G$49
Name m.o: 'Lista de composição de preço'!$G$48

Sheet MQT
B2: CO26/0034
B3: Cliente: Tiago Parada | J3: Analise financeira | P3: FI Estrutura | R3: Negociação | S3: Lucro | T3: Custo Fixo | U3: K médio
B4: Morada: Rua António José de Almeida, 3º Direito, Brandoa, 2650-381 | P4: 1.15 | R4: 1 | S4: =J30-T4 -> 227.43 | T4: =(F28*P4)-F28 -> 227.43 | U4: =H28/F28 -> 1.3
B5: Responsável: Vinícius Tomaz | P5: Margem - K
H6: MD05.00 | P6: Const. civil | Q6: Águas | R6: Gás | S6: Eletricidade | T6: AVAC | U6: SCIE
A7: ITEM | B7: DESCRIÇÃO | C7: UN | D7: QTD | E7: VALOR UNITÁRIO CUSTO | F7: VALOR TOTAL CUSTO | G7: VALOR UNITÁRIO | H7: VALOR TOTAL | J7: Rentabilidade Estimada € | K7: Rentabilidade Estimada % | M7: COMENTÁRIOS | N7: Margem Cap. | P7: 1.15 | Q7: 1.25 | R7: 1.25 | S7: 1.25 | T7: 1.25 | U7: 1.25
A8: 1 | B8: Quarto 01 - Crianças | F8: =SUM(F9:F11) -> 759.21 | H8: =SUM(H9:H11) -> 986.973 | J8: =SUM(J9:J11) -> 227.763 | N8: =$P$7*R4 -> 1.15 | W8: Quadro de áreas
A9: 1.1 | B9: Solução para tetos interiores, constituída por estrutura com perfis metálicos horizontais F530 afastados a cada 500 mm, suspensos por elementos verticais fixados ao teto, nos quais é fixada 1 camada de placas Gyptec BA13A (STANDARD). Massas, bandas para juntas e acessórios de fixação. Superfícies prontas para acabamento final de pintura ou decoração | C9: vg | D9: 1 | E9: =M.Calculo!H22 -> 382 | F9: =D9*E9 -> 382 | G9: =((E9*$P$4*$R$4)-E9)+(E9*$N$8) -> 496.6 | H9: =G9*D9 -> 496.6 | J9: =H9-F9 -> 114.6 | K9: =(H9/F9)-100% -> 0.3 | W9: Divisão | X9: Comprimento | Y9: Largura | Z9: Altura | AA9: Área | AB9: Paredes | AC9: Teto | AD9: Perímetro
A10: 1.2 | B10: Execução de esquema de pintura em teto com Tinta Robbialac 2 em 1 branco, aplicado em 2 demão. Inclui proteção de rodapé, caixilharias, guarnições de portas, utilizando fita multisuperficies, e manga plástica para pavimento | C10: vg | D10: 1 | E10: =M.Calculo!H45 -> 214.5 | F10: =D10*E10 -> 214.5 | G10: =((E10*$P$4*$R$4)-E10)+(E10*$N$8) -> 278.85 | H10: =G10*D10 -> 278.85 | J10: =H10-F10 -> 64.35 | K10: =(H10/F10)-100% -> 0.3 | W10: Quarto | X10: 4 | Y10: 3 | Z10: 2.6 | AA10: =X10*Y10 -> 12 | AB10: =((X10*Z10)+(Y10*Z10))*2 -> 36.4 | AC10: =X10*Y10 -> 12 | AD10: =(X10+Y10)*2 -> 14
A11: 1.3 | B11: Fornecimento de Sanca HOMESTAR A5 200X3.5X3.5cm em todo perimetro do teto falso. | C11: vg | D11: 1 | E11: =M.Calculo!H68 -> 162.71 | F11: =D11*E11 -> 162.71 | G11: =((E11*$P$4*$R$4)-E11)+(E11*$N$8) -> 211.523 | H11: =G11*D11 -> 211.523 | J11: =H11-F11 -> 48.813 | K11: =(H11/F11)-100% -> 0.3 | W11: Quarto 2 | X11: =2.5+3 -> 5.5 | Y11: 2.1 | Z11: 2.6 | AA11: =X11*Y11 -> 11.55 | AB11: =((X11*Z11)+(Y11*Z11))*2 -> 39.52 | AC11: =X11*Y11 -> 11.55 | AD11: =(X11+Y11)*2 -> 15.2
A12: 2 | F12: =SUM(F13:F16) -> 756.99 | H12: =SUM(H13:H16) -> 984.087 | J12: =SUM(J13:J16) -> 227.097 | N12: =$P$7*R4 -> 1.15 | AA12: =X12*Y12 -> 0 | AB12: =((X12*Z12)+(Y12*Z12))*2 -> 0 | AC12: =X12*Y12 -> 0 | AD12: =(X12+Y12)*2 -> 0
A13: 2.1 | B13: Solução para tetos interiores, constituída por estrutura com perfis metálicos horizontais F530 afastados a cada 500 mm, suspensos por elementos verticais fixados ao teto, nos quais é fixada 1 camada de placas Gyptec BA13A (STANDARD). Massas, bandas para juntas e acessórios de fixação. Superfícies prontas para acabamento final de pintura ou decoração | C13: vg | D13: 1 | E13: =M.Calculo!H91 -> 382 | F13: =D13*E13 -> 382 | G13: =((E13*$P$4*$R$4)-E13)+(E13*$N$8) -> 496.6 | H13: =G13*D13 -> 496.6 | J13: =H13-F13 -> 114.6 | K13: =(H13/F13)-100% -> 0.3 | AA13: =X13*Y13 -> 0 | AB13: =((X13*Z13)+(Y13*Z13))*2 -> 0 | AC13: =X13*Y13 -> 0 | AD13: =(X13+Y13)*2 -> 0
A14: 2.2 | B14: Execução de esquema de pintura em teto com Tinta Robbialac 2 em 1 branco, aplicado em 2 demão. Inclui proteção de rodapé, caixilharias, guarnições de portas, utilizando fita multisuperficies, e manga plástica para pavimento | C14: vg | D14: 1 | E14: =M.Calculo!H114 -> 209.5 | F14: =D14*E14 -> 209.5 | G14: =((E14*$P$4*$R$4)-E14)+(E14*$N$8) -> 272.35 | H14: =G14*D14 -> 272.35 | J14: =H14-F14 -> 62.85 | K14: =(H14/F14)-100% -> 0.3 | AA14: =X14*Y14 -> 0 | AB14: =((X14*Z14)+(Y14*Z14))*2 -> 0 | AC14: =X14*Y14 -> 0 | AD14: =(X14+Y14)*2 -> 0
A15: 2.3 | B15: Fornecimento de Sanca HOMESTAR A5 200X3.5X3.5cm em todo perimetro do teto falso. | C15: vg | D15: 1 | E15: =M.Calculo!H137 -> 165.49 | F15: =D15*E15 -> 165.49 | G15: =((E15*$P$4*$R$4)-E15)+(E15*$N$8) -> 215.137 | H15: =G15*D15 -> 215.137 | J15: =H15-F15 -> 49.647 | K15: =(H15/F15)-100% -> 0.3 | AA15: =X15*Y15 -> 0 | AB15: =((X15*Z15)+(Y15*Z15))*2 -> 0 | AC15: =X15*Y15 -> 0 | AD15: =(X15+Y15)*2 -> 0
AA16: =X16*Y16 -> 0 | AB16: =((X16*Z16)+(Y16*Z16))*2 -> 0 | AC16: =X16*Y16 -> 0 | AD16: =(X16+Y16)*2 -> 0
W17: TOTAL | AA17: =SUM(AA10:AA16) -> 23.55 | AB17: =SUM(AB10:AB16) -> 75.92 | AC17: =SUM(AC10:AC16) -> 23.55 | AD17: =SUM(AD10:AD16) -> 29.2
A20: Notas: | J20: Imposto sobre orçamento
A21: 1 - | B21: A proposta só é válida em sua globalidade, reservando a empresa o direito de rever os valores em caso de adjudicação parcial. | K21: IVA | L21: 0.23
A22: 2 - | B22: Todos os trabalhos foram considerados em horário normal. | K22: IVA | L22: 0.06
A23: 3 - | B23: Condições de pagamento: 50% na adjudicação a P.P. e, 50% nos términos dos trabalhos a P.P. *P.P. (Pronto pagamento) | J23: Total a Faturar | M23: =M22+J22 -> 0
A24: 4 - | B24: Todos os itens omissos serão apresentados em forma de proposta para avaliação do cliente. | J24: Condições de pagamento
A25: 5 - | B25: Não está considerado movimentação de móveis e/ou bens pessoais | J25: 1º Fatura | K25: 0.5 | M25: =K25*H28 -> 985.53
J26: 2º Fatura | K26: 0.5 | M26: =K26*H28 -> 985.53
F27: TOTAL CUSTO | H27: TOTAL PROPOSTA | J27: 3º Fatura | K27: 0 | M27: =K27*H28 -> 0
F28: =F17+F12+F8 -> 1516.2 | H28: =SUM(H17,H12,H8) -> 1971.06
J29: LUCRO ESTIMADO
J30: =SUM(J17,J12,J8) -> 454.86

Sheet M.Calculo
B2: ITEM | C2: DESCRIÇÃO | D2: UN | E2: QTD | G2: V.UN | H2: V.TOTAL | I2: Consumos /rendimentos | K2: Tempo em dias | L2: Vazadouro | N2: Ref. ITEM
E3: Qtd padrão | F3: Qtd pontual | I3: Valor | J3: Unidade | L3: Material | M3: Volume m3
B4: =MQT!B9 -> Solução para tetos interiores, constituída por estrutura com perfis metálicos horizontais F530 afastados a cada 500 mm, suspensos por elementos verticais fixados ao teto, nos quais é fixada 1 camada de placas Gyptec BA13A (STANDARD). Massas, bandas para juntas e acessórios de fixação. Superfícies prontas para acabamento final de pintura ou decoração | C4: Mão de obra | H4: =SUM(H5:H6) -> 216 | K4: =((E5+E6)/2)/8 -> 1
C5: M.Oficial | D5: h | E5: 8 | F5: 1 | G5: 15 | H5: =G5*E5*F5 -> 120
C6: M.Ajudante | D6: h | E6: 8 | F6: 1 | G6: 12 | H6: =G6*E6*F6 -> 96
C7: Materiais | H7: =SUM(H8:H10) -> 125
C8: Material para teto falso | D8: un | E8: 1 | F8: 1 | G8: 125 | H8: =G8*E8*F8 -> 125
H9: =G9*E9*F9 -> 0
H10: =G10*E10*F10 -> 0
C11: Aluguel | H11: =SUM(H12:H14) -> 0
C12: Martelo demolidor 6kg aluguer | D12: dia | E12: 1 | F12: 0 | G12: 25 | H12: =G12*E12*F12 -> 0
C13: Broca martelo | D13: cj | E13: 1 | F13: 0 | G13: 4 | H13: =G13*E13*F13 -> 0
C15: Vazadouro | H15: =SUM(H16:H17) -> 11 | L15: Reboco | M15: =2*5*0.02*1.1 -> 0.22
C16: Vazadouro | D16: vg | E16: =ROUNDUP((SUM(M4:M23)/300),0) -> 1 | F16: 1 | G16: 5 | H16: =G16*E16*F16 -> 5
C17: Transporte de lixo | D17: h | E17: 1 | F17: 0.5 | G17: 12 | H17: =G17*E17*F17 -> 6
C18: Transporte | H18: =SUM(H19) -> 20
C19: Transporte TKH | D19: dia | E19: 1 | F19: 1 | G19: =(20*E5)/8 -> 20 | H19: =G19*E19*F19 -> 20
C20: Extras - Diversos | H20: =SUM(H21) -> 10
C21: Acessórios | D21: vg | E21: 1 | F21: 1 | G21: 10 | H21: =G21*E21*F21 -> 10
C22: Total | H22: =SUM(H4,H7,H11,H15,H18,H20) -> 382
C23: Total/m2 | G23: =MQT!AA10 -> 12 | H23: =ROUNDUP((H22/G23),0) -> 32
B25: ITEM | C25: DESCRIÇÃO | D25: UN | E25: QTD | G25: V.UN | H25: V.TOTAL | I25: Consumos /rendimentos | K25: Tempo em dias | L25: Vazadouro | N25: Ref. ITEM
E26: Qtd padrão | F26: Qtd pontual | I26: Valor | J26: Unidade | L26: Material | M26: Volume m3
B27: =MQT!B10 -> Execução de esquema de pintura em teto com Tinta Robbialac 2 em 1 branco, aplicado em 2 demão. Inclui proteção de rodapé, caixilharias, guarnições de portas, utilizando fita multisuperficies, e manga plástica para pavimento | C27: Mão de obra | H27: =SUM(H28:H29) -> 108 | K27: =((E28+E29)/2)/8 -> 0.5
C28: M.Oficial | D28: h | E28: 4 | F28: 1 | G28: 15 | H28: =G28*E28*F28 -> 60
C29: M.Ajudante | D29: h | E29: 4 | F29: 1 | G29: 12 | H29: =G29*E29*F29 -> 48
C30: Materiais | H30: =SUM(H31:H33) -> 49.5
C31: Tinta interior parede Branco facil robbialac branco mate 15L | D31: un | E31: 1 | F31: 1 | G31: =99/2 -> 49.5 | H31: =G31*E31*F31 -> 49.5
H32: =G32*E32*F32 -> 0
H33: =G33*E33*F33 -> 0
C34: Aluguel | H34: =SUM(H35:H37) -> 0
C35: Martelo demolidor 10kg aluguer | D35: dia | E35: 1 | F35: 0 | G35: 25 | H35: =G35*E35*F35 -> 0
C36: Broca martelo | D36: cj | E36: 1 | F36: 0 | G36: 4 | H36: =G36*E36*F36 -> 0
C38: Vazadouro | H38: =SUM(H39:H40) -> 17 | L38: Reboco | M38: =2*5*0.02*1.1 -> 0.22
C39: Vazadouro | D39: vg | E39: =ROUNDUP((SUM(M27:M46)/300),0) -> 1 | F39: 1 | G39: 5 | H39: =G39*E39*F39 -> 5
C40: Transporte de lixo | D40: h | E40: 1 | F40: 1 | G40: 12 | H40: =G40*E40*F40 -> 12
C41: Transporte | H41: =SUM(H42) -> 10
C42: Transporte TKH | D42: dia | E42: 1 | F42: 1 | G42: =(20*E28)/8 -> 10 | H42: =G42*E42*F42 -> 10
C43: Extras - Diversos | H43: =SUM(H44) -> 30
C44: Acessórios | D44: vg | E44: 1 | F44: 1 | G44: 30 | H44: =G44*E44*F44 -> 30
C45: Total | H45: =SUM(H27,H30,H34,H38,H41,H43) -> 214.5
C46: Total/m2 | G46: =G23 -> 12 | H46: =ROUNDUP((H45/G46),0) -> 18
B48: =MQT!A11 -> 1.3 | C48: DESCRIÇÃO | D48: UN | E48: QTD | G48: V.UN | H48: V.TOTAL | I48: Consumos /rendimentos | K48: Tempo em dias | L48: Vazadouro | N48: Ref. ITEM
E49: Qtd padrão | F49: Qtd pontual | I49: Valor | J49: Unidade | L49: Material | M49: Volume m3
B50: =MQT!B11 -> Fornecimento de Sanca HOMESTAR A5 200X3.5X3.5cm em todo perimetro do teto falso. | C50: Mão de obra | H50: =SUM(H51:H52) -> 108 | K50: =((E51+E52)/2)/8 -> 0.5
C51: M.Oficial | D51: h | E51: 4 | F51: 1 | G51: 15 | H51: =G51*E51*F51 -> 60
C52: M.Ajudante | D52: h | E52: 4 | F52: 1 | G52: 12 | H52: =G52*E52*F52 -> 48
C53: Materiais | H53: =SUM(H54:H56) -> 17.71
C54: Sanca HOMESTAR A5 200X3.5X3.5CM | D54: un | E54: 1 | F54: 7 | G54: 1.39 | H54: =G54*E54*F54 -> 9.73
C55: Cola para Sanca | D55: un | E55: 1 | F55: 2 | G55: 3.99 | H55: =G55*E55*F55 -> 7.98
H56: =G56*E56*F56 -> 0
C57: Aluguel | H57: =SUM(H58:H60) -> 0
C58: Martelo demolidor 10kg aluguer | D58: dia | E58: 1 | F58: 0 | G58: 25 | H58: =G58*E58*F58 -> 0
C59: Broca martelo | D59: cj | E59: 1 | F59: 0 | G59: 4 | H59: =G59*E59*F59 -> 0
C61: Vazadouro | H61: =SUM(H62:H63) -> 17 | L61: Reboco | M61: =2*5*0.02*1.1 -> 0.22
C62: Vazadouro | D62: vg | E62: =ROUNDUP((SUM(M50:M69)/300),0) -> 1 | F62: 1 | G62: 5 | H62: =G62*E62*F62 -> 5
C63: Transporte de lixo | D63: h | E63: 1 | F63: 1 | G63: 12 | H63: =G63*E63*F63 -> 12
C64: Transporte | H64: =SUM(H65) -> 10
C65: Transporte TKH | D65: dia | E65: 1 | F65: 1 | G65: =(20*E51)/8 -> 10 | H65: =G65*E65*F65 -> 10
C66: Extras - Diversos | H66: =SUM(H67) -> 10
C67: Acessórios | D67: vg | E67: 1 | F67: 1 | G67: 10 | H67: =G67*E67*F67 -> 10
C68: Total | H68: =SUM(H50,H53,H57,H61,H64,H66) -> 162.71
C69: Total/m | G69: 14 | H69: =ROUNDUP((H68/G69),0) -> 12
B71: =MQT!A13 -> 2.1 | C71: DESCRIÇÃO | D71: UN | E71: QTD | G71: V.UN | H71: V.TOTAL | I71: Consumos /rendimentos | K71: Tempo em dias | L71: Vazadouro | N71: Ref. ITEM
E72: Qtd padrão | F72: Qtd pontual | I72: Valor | J72: Unidade | L72: Material | M72: Volume m3
B73: =MQT!B13 -> Solução para tetos interiores, constituída por estrutura com perfis metálicos horizontais F530 afastados a cada 500 mm, suspensos por elementos verticais fixados ao teto, nos quais é fixada 1 camada de placas Gyptec BA13A (STANDARD). Massas, bandas para juntas e acessórios de fixação. Superfícies prontas para acabamento final de pintura ou decoração | C73: Mão de obra | H73: =SUM(H74:H75) -> 216 | K73: =((E74+E75)/2)/8 -> 1
C74: M.Oficial | D74: h | E74: 8 | F74: 1 | G74: 15 | H74: =G74*E74*F74 -> 120
C75: M.Ajudante | D75: h | E75: 8 | F75: 1 | G75: 12 | H75: =G75*E75*F75 -> 96
C76: Materiais | H76: =SUM(H77:H79) -> 125
C77: Material para teto falso | D77: un | E77: 1 | F77: 1 | G77: 125 | H77: =G77*E77*F77 -> 125
H78: =G78*E78*F78 -> 0
H79: =G79*E79*F79 -> 0
C80: Aluguel | H80: =SUM(H81:H83) -> 0
C81: Martelo demolidor 6kg aluguer | D81: dia | E81: 1 | F81: 0 | G81: 25 | H81: =G81*E81*F81 -> 0
C82: Broca martelo | D82: cj | E82: 1 | F82: 0 | G82: 4 | H82: =G82*E82*F82 -> 0
C84: Vazadouro | H84: =SUM(H85:H86) -> 11 | L84: Reboco | M84: =2*5*0.02*1.1 -> 0.22
C85: Vazadouro | D85: vg | E85: =ROUNDUP((SUM(M73:M92)/300),0) -> 1 | F85: 1 | G85: 5 | H85: =G85*E85*F85 -> 5
C86: Transporte de lixo | D86: h | E86: 1 | F86: 0.5 | G86: 12 | H86: =G86*E86*F86 -> 6
C87: Transporte | H87: =SUM(H88) -> 20
C88: Transporte TKH | D88: dia | E88: 1 | F88: 1 | G88: =(20*E74)/8 -> 20 | H88: =G88*E88*F88 -> 20
C89: Extras - Diversos | H89: =SUM(H90) -> 10
C90: Acessórios | D90: vg | E90: 1 | F90: 1 | G90: 10 | H90: =G90*E90*F90 -> 10
C91: Total | H91: =SUM(H73,H76,H80,H84,H87,H89) -> 382
C92: Total/m2 | G92: =MQT!AA11 -> 11.55 | H92: =ROUNDUP((H91/G92),0) -> 34
B94: =MQT!A14 -> 2.2 | C94: DESCRIÇÃO | D94: UN | E94: QTD | G94: V.UN | H94: V.TOTAL | I94: Consumos /rendimentos | K94: Tempo em dias | L94: Vazadouro | N94: Ref. ITEM
E95: Qtd padrão | F95: Qtd pontual | I95: Valor | J95: Unidade | L95: Material | M95: Volume m3
B96: =MQT!B14 -> Execução de esquema de pintura em teto com Tinta Robbialac 2 em 1 branco, aplicado em 2 demão. Inclui proteção de rodapé, caixilharias, guarnições de portas, utilizando fita multisuperficies, e manga plástica para pavimento | C96: Mão de obra | H96: =SUM(H97:H98) -> 108 | K96: =((E97+E98)/2)/8 -> 0.5
C97: M.Oficial | D97: h | E97: 4 | F97: 1 | G97: 15 | H97: =G97*E97*F97 -> 60
C98: M.Ajudante | D98: h | E98: 4 | F98: 1 | G98: 12 | H98: =G98*E98*F98 -> 48
C99: Materiais | H99: =SUM(H100:H102) -> 44.5
C100: Tinta interior parede Branco facil robbialac branco mate 15L | D100: un | E100: 1 | F100: 1 | G100: 44.5 | H100: =G100*E100*F100 -> 44.5
H101: =G101*E101*F101 -> 0
H102: =G102*E102*F102 -> 0
C103: Aluguel | H103: =SUM(H104:H106) -> 0
C104: Martelo demolidor 10kg aluguer | D104: dia | E104: 1 | F104: 0 | G104: 25 | H104: =G104*E104*F104 -> 0
C105: Broca martelo | D105: cj | E105: 1 | F105: 0 | G105: 4 | H105: =G105*E105*F105 -> 0
C107: Vazadouro | H107: =SUM(H108:H109) -> 17 | L107: Reboco | M107: =2*5*0.02*1.1 -> 0.22
C108: Vazadouro | D108: vg | E108: =ROUNDUP((SUM(M96:M115)/300),0) -> 1 | F108: 1 | G108: 5 | H108: =G108*E108*F108 -> 5
C109: Transporte de lixo | D109: h | E109: 1 | F109: 1 | G109: 12 | H109: =G109*E109*F109 -> 12
C110: Transporte | H110: =SUM(H111) -> 10
...

Sheet Lista de composição de preço
B2: Demolição
B4: ITEM | C4: DESCRIÇÃO | D4: UN | E4: QTD | G4: V.UN | H4: V.TOTAL | I4: Consumos /rendimentos | K4: Tempo em dias | L4: Vazadouro | N4: Ref. ITEM
E5: Qtd padrão | F5: Qtd pontual | I5: Valor | J5: Unidade | L5: Material | M5: Volume
B6: Montagem e desmontagem de estaleiro provisório, incluindo a organização inicial do canteiro de obras com definição de áreas de armazenamento. Considera-se fornecimento de meios elevatórios para execução dos trabalhos, todos homolagos pelo CE e seguindo as normas de SST. | C6: M.Oficial | D6: h | E6: 4 | F6: 1 | G6: 17 | H6: =G6*E6*F6 -> 68 | K6: =((E6+E7)/2)/8 -> 0.5
C7: M.Ajudante | D7: h | E7: 4 | F7: 1 | G7: 12 | H7: =G7*E7*F7 -> 48
C8: Escada multifunções MULTIUSOS 4X3 COM PLATAFORMA 3.49M | D8: dia | E8: 10 | F8: 1 | G8: =150/365 -> 0.4109589 | H8: =G8*E8*F8 -> 4.109589
C9: Andaime - transporte | D9: un | F9: 2 | G9: 55 | H9: =G9*E9*F9 -> 0
C10: Aluguer aindame | D10: dia | F10: 1 | G10: 5.5 | H10: =G10*E10*F10 -> 0
C11: Andaime dobrável 90x190 plataforma 190 C/E - 4,70 m altura de trabalho | D11: dia | F11: 1 | G11: =1950/365 -> 5.3424658 | H11: =G11*E11*F11 -> 0 | N11: https://www.iberandamios.com/pt/andaime-dobravel-90-cm/andaime-dobravel-90x190-plataforma-190-ce-470-m-altura-de-trabalho/
C12: Vazadouro | D12: un | E12: =ROUNDUP((SUM(M6:M16)/300),0) -> 0 | G12: 200 | H12: =G12*E12*F12 -> 0
C13: Transporte TKH | D13: un | E13: 1 | F13: 1 | G13: 20 | H13: =G13*E13*F13 -> 20
C14: Acessórios | D14: vg | E14: 1 | F14: 1 | G14: 10 | H14: =G14*E14*F14 -> 10
C15: Total | H15: =SUM(H6:H14) -> 150.10959
C16: Total/m2 | E16: Área | G16: 10 | H16: =ROUNDUP((H15/G16),0) -> 16
B18: ITEM | C18: DESCRIÇÃO | D18: UN | E18: QTD | G18: V.UN | H18: V.TOTAL | I18: Consumos /rendimentos | K18: Tempo em dias | L18: Vazadouro | N18: Ref. ITEM
E19: Qtd padrão | F19: Qtd pontual | I19: Valor | J19: Unidade | L19: Material | M19: Volume
B20: Fornecimento de meios elevatórios tipo: Braço articulado 12m a Disel, incluindo carga, transporte e recolha de equipamento em obra. | C20: M.Oficial | D20: h | E20: 4 | F20: 1 | G20: 17 | H20: =G20*E20*F20 -> 68
C21: M.Ajudante | D21: h | E21: 0 | F21: 1 | G21: 12 | H21: =G21*E21*F21 -> 0
C22: Braço articulado 12 m disel - GoingUp | D22: dias | E22: 1 | F22: 1 | G22: 65 | H22: =G22*E22*F22 -> 65
C23: Entrega de equipamento | D23: un | E23: 1 | F23: 1 | G23: 150 | H23: =G23*E23*F23 -> 150
C24: Recolha de equipamento | D24: un | E24: 1 | F24: 1 | G24: 150 | H24: =G24*E24*F24 -> 150
H25: =G25*E25*F25 -> 0
H26: =G26*E26*F26 -> 0
C27: Transporte TKH | D27: un | E27: 1 | F27: 1 | G27: 20 | H27: =G27*E27*F27 -> 20
C28: Acessórios | D28: vg | E28: 1 | F28: 1 | G28: 10 | H28: =G28*E28*F28 -> 10
C29: Total | H29: =SUM(H20:H28) -> 463
C30: Total/m2 | E30: Área | G30: 10 | H30: =ROUNDUP((H29/G30),0) -> 47
B32: ITEM | C32: DESCRIÇÃO | D32: UN | E32: QTD | G32: V.UN | H32: V.TOTAL | I32: Consumos /rendimentos | K32: Tempo em dias | L32: Vazadouro | N32: Ref. ITEM
E33: Qtd padrão | F33: Qtd pontual | I33: Valor | J33: Unidade | L33: Material | M33: Volume
B34: Picagem de reboco existente paredes e/ou tetos, utilizando martelo pneumático de 8 kg. O serviço inclui carga, transporte e descarte dos materiais resultantes em vazadouro autorizado. | C34: M.Oficial | D34: h | E34: 4 | F34: 1 | G34: 17 | H34: =G34*E34*F34 -> 68 | K34: =((E34+E35)/2)/8 -> 0.5 | M34: =0.02*2*5*1.1 -> 0.22
C35: M.Ajudante | D35: h | E35: 4 | F35: 0 | G35: 12 | H35: =G35*E35*F35 -> 0
C36: Martelo demolidor 10kg aluguer | D36: dia | E36: 1 | F36: 1 | G36: 25 | H36: =G36*E36*F36 -> 25
C37: Broca martelo | D37: un | E37: 1 | F37: 1 | G37: 4 | H37: =G37*E37*F37 -> 4
C39: Vazadouro | D39: un | E39: =ROUNDUP((SUM(M34:M44)/300),0) -> 1 | F39: 1 | G39: =200*M34/6 -> 7.3333333 | H39: =G39*E39*F39 -> 7.3333333
C40: Transporte de lixo | D40: h | E40: 1 | F40: 1 | G40: 10 | H40: =G40*E40*F40 -> 10
C41: Transporte TKH | D41: un | E41: 1 | F41: 1 | G41: 20 | H41: =G41*E41*F41 -> 20
C42: Acessórios | D42: vg | E42: 1 | F42: 0 | G42: 10 | H42: =G42*E42*F42 -> 0
C43: Total | H43: =SUM(H34:H42) -> 134.33333
C44: Total/m2 | E44: Área | G44: 10 | H44: =ROUNDUP((H43/G44),0) -> 14
B46: ITEM | C46: DESCRIÇÃO | D46: UN | E46: QTD | G46: V.UN | H46: V.TOTAL | I46: Consumos /rendimentos | K46: Tempo em dias | L46: Vazadouro | N46: Ref. ITEM
E47: Qtd padrão | F47: Qtd pontual | I47: Valor | J47: Unidade | L47: Material | M47: Volume
B48: Picagem de betonilha existente com espessura aproximada de 5 cm, utilizando martelo pneumático de 8 kg. O serviço inclui carga, transporte e descarte dos materiais resultantes em vazadouro autorizado. | C48: M.Oficial | D48: h | E48: 16 | F48: 1 | G48: 17 | H48: =G48*E48*F48 -> 272 | K48: =((E48+E49)/2)/8 -> 2 | L48: betonilha 5cm | M48: =10*10*0.05*1.1 -> 5.5
C49: M.Ajudante | D49: h | E49: 16 | F49: 2 | G49: 12 | H49: =G49*E49*F49 -> 384
C50: Martelo demolidor 10kg aluguer | D50: dia | E50: 2 | F50: 3 | G50: 25 | H50: =G50*E50*F50 -> 150
C51: Broca martelo | D51: un | E51: 2 | F51: 3 | G51: 4 | H51: =G51*E51*F51 -> 24
C52: Material 3 | D52: m3 | E52: 1 | G52: 1 | H52: =G52*E52*F52 -> 0
C53: Vazadouro | D53: un | E53: =ROUNDUP((SUM(M48:M58)/300),0) -> 1 | F53: 1 | G53: =200*M48/6 -> 183.33333 | H53: =G53*E53*F53 -> 183.33333
C54: Transporte de lixo | D54: h | E54: 8 | F54: 1 | G54: 10 | H54: =G54*E54*F54 -> 80
C55: Transporte TKH | D55: un | E55: 1 | F55: 2 | G55: 20 | H55: =G55*E55*F55 -> 40
C56: Acessórios | D56: vg | E56: 1 | F56: 1 | G56: 10 | H56: =G56*E56*F56 -> 10
C57: Total | H57: =SUM(H48:H56) -> 1143.3333
C58: Total/m2 | E58: Área | G58: 100 | H58: =ROUNDUP((H57/G58),0) -> 12
B60: ITEM | C60: DESCRIÇÃO | D60: UN | E60: QTD | G60: V.UN | H60: V.TOTAL | I60: Consumos /rendimentos | K60: Tempo em dias | L60: Vazadouro | N60: Ref. ITEM
E61: Qtd padrão | F61: Qtd pontual | I61: Valor | J61: Unidade | L61: Material | M61: Volume
B62: Abertura e fecho de roço em pavimento 5x3cm (betonilha), para passagem de tubagens, executado com recurso a ferramentas elétricas (com rebarbadora e martelo elétrico), incluindo remoção e transporte do entulho, fixação da tubagem, fecho com argamassa pré-dosada SecilTEK Classic, misturada manualmente com adição de água conforme instruções do fabricante e regularização da superfície, pronta a receber novo revestimento. | C62: M.Oficial | D62: h | E62: 16 | F62: 1 | G62: 17 | H62: =G62*E62*F62 -> 272 | K62: =((E62+E63)/2)/8 -> 1.5 | M62: 0.5
C63: M.Ajudante | D63: h | E63: 8 | F63: 1 | G63: 12 | H63: =G63*E63*F63 -> 96
C64: Betonilha interior/exterior 25 kg cinza Seciltek classic | D64: un | E64: =ROUNDUP((SUM(0.5*I64*5)/25),0) -> 2 | F64: 1 | G64: 2.59 | H64: =G64*E64*F64 -> 5.18 | I64: 20 | J64: kg/m2/cm
C65: Martelo demolidor 10kg aluguer | D65: dia | E65: 1 | F65: 1 | G65: 25 | H65: =G65*E65*F65 -> 25
C66: Broca martelo | D66: un | E66: 1 | F66: 1 | G66: 4 | H66: =G66*E66*F66 -> 4
C67: Rebardadora + disco | D67: un | E67: 1 | F67: 1 | G67: 4 | H67: =G67*E67*F67 -> 4
C68: Vazadouro | D68: un | E68: 1 | F68: 1 | G68: =200*M62/6 -> 16.666667 | H68: =G68*E68*F68 -> 16.666667
C69: Transporte TKH | D69: un | E69: 1 | F69: 2 | G69: 20 | H69: =G69*E69*F69 -> 40
C70: Acessórios | D70: vg | E70: 1 | F70: 1 | G70: 10 | H70: =G70*E70*F70 -> 10
C71: Total | H71: =SUM(H62:H70) -> 472.84667
C72: Total/m | E72: metros | G72: 10 | H72: =ROUNDUP((H71/G72),0) -> 48
B74: ITEM | C74: DESCRIÇÃO | D74: UN | E74: QTD | G74: V.UN | H74: V.TOTAL | I74: Consumos /rendimentos | K74: Tempo em dias | L74: Vazadouro | N74: Ref. ITEM
E75: Qtd padrão | F75: Qtd pontual | I75: Valor | J75: Unidade | L75: Material | M75: Volume
B76: Abertura e fecho de roço em pavimento 5x5cm (betão), para passagem de tubagens, executado com recurso a ferramentas elétricas (com rebarbadora e martelo elétrico), incluindo remoção e transporte do entulho, fixação da tubagem, fecho com argamassa pré-dosada SecilTEK Classic, misturada manualmente com adição de água conforme instruções do fabricante e regularização da superfície, pronta a receber novo revestimento. | C76: M.Oficial | D76: h | E76: 16 | F76: 1 | G76: 17 | H76: =G76*E76*F76 -> 272 | K76: =((E76+E77)/2)/8 -> 2 | M76: 0.5
C77: M.Ajudante | D77: h | E77: 16 | F77: 1 | G77: 12 | H77: =G77*E77*F77 -> 192
C78: Betonilha interior/exterior 25 kg cinza Seciltek classic | D78: un | E78: =ROUNDUP((SUM(0.5*I78*5)/25),0) -> 2 | F78: 1 | G78: 2.59 | H78: =G78*E78*F78 -> 5.18 | I78: 20 | J78: kg/m2/cm
C79: Martelo demolidor 10kg aluguer | D79: dia | E79: 1 | F79: 1 | G79: 25 | H79: =G79*E79*F79 -> 25
C80: Broca martelo | D80: un | E80: 1 | F80: 1 | G80: 4 | H80: =G80*E80*F80 -> 4
C81: Rebardadora + disco | D81: un | E81: 1 | F81: 1 | G81: 4 | H81: =G81*E81*F81 -> 4
C82: Vazadouro | D82: un | E82: 1 | F82: 1 | G82: =200*M76/6 -> 16.666667 | H82: =G82*E82*F82 -> 16.666667
C83: Transporte TKH | D83: un | E83: 1 | F83: 2 | G83: 20 | H83: =G83*E83*F83 -> 40
C84: Acessórios | D84: vg | E84: 1 | F84: 1 | G84: 10 | H84: =G84*E84*F84 -> 10
C85: Total | H85: =SUM(H76:H84) -> 568.84667
C86: Total/m | E86: metros | G86: 10 | H86: =ROUNDUP((H85/G86),0) -> 57
B88: ITEM | C88: DESCRIÇÃO | D88: UN | E88: QTD | G88: V.UN | H88: V.TOTAL | I88: Consumos /rendimentos | K88: Tempo em dias | L88: Vazadouro | N88: Ref. ITEM
E89: Qtd padrão | F89: Qtd pontual | I89: Valor | J89: Unidade | L89: Material | M89: Volume
B90: Abertura e fecho de roço em alvenaria 5x3cm, para passagem de tubagens, executado com recurso a ferramentas elétricas (com rebarbadora e martelo elétrico), incluindo remoção e transporte do entulho, fixação da tubagem, fecho com argamassa pré-dosada SecilTEK Redur, misturada manualmente com adição de água conforme instruções do fabricante e regularização da superfície, pronta a receber novo revestimento. | C90: M.Oficial | D90: h | E90: 8 | F90: 1 | G90: 17 | H90: =G90*E90*F90 -> 136 | K90: =((E90+E91)/2)/8 -> 1 | M90: 0.5
C91: M.Ajudante | D91: h | E91: 8 | F91: 1 | G91: 12 | H91: =G91*E91*F91 -> 96
C92: Betonilha interior/exterior 25 kg cinza Seciltek classic | D92: un | E92: =ROUNDUP((SUM(0.5*I92*5)/25),0) -> 2 | F92: 1 | G92: 2.59 | H92: =G92*E92*F92 -> 5.18 | I92: 20 | J92: kg/m2/cm
C93: Martelo demolidor 10kg aluguer | D93: dia | E93: 1 | F93: 1 | G93: 25 | H93: =G93*E93*F93 -> 25
C94: Broca martelo | D94: un | E94: 1 | F94: 1 | G94: 4 | H94: =G94*E94*F94 -> 4
C95: Rebardadora + disco | D95: un | E95: 1 | F95: 1 | G95: 4 | H95: =G95*E95*F95 -> 4
C96: Vazadouro | D96: un | E96: 1 | F96: 1 | G96: =200*M90/6 -> 16.666667 | H96: =G96*E96*F96 -> 16.666667
C97: Transporte TKH | D97: un | E97: 1 | F97: 1 | G97: 20 | H97: =G97*E97*F97 -> 20
C98: Acessórios | D98: vg | E98: 1 | F98: 1 | G98: 4 | H98: =G98*E98*F98 -> 4
C99: Total | H99: =SUM(H90:H98) -> 310.84667
C100: Total/m | E100: Metros | G100: 10 | H100: =ROUNDUP((H99/G100),0) -> 32
B102: ITEM | C102: DESCRIÇÃO | D102: UN | E102: QTD | G102: V.UN | H102: V.TOTAL | I102: Consumos /rendimentos | K102: Tempo em dias | L102: Vazadouro | N102: Ref. ITEM
E103: Qtd padrão | F103: Qtd pontual | I103: Valor | J103: Unidade | L103: Material | M103: Volume
B104: Abertura e fecho de roço em parede de betão 5x5cm, para passagem de tubagens ou condutas, executado com recurso a ferramentas elétricas (com rebarbadora e martelo elétrico), incluindo remoção e transporte do entulho, fixação da tubagem, fecho com argamassa pré-dosada SecilTEK Redur, misturada manualmente com adição de água conforme instruções do fabricante e regularização da superfície, pronta a receber novo revestimento. | C104: M.Oficial | D104: h | E104: 16 | F104: 1 | G104: 17 | H104: =G104*E104*F104 -> 272 | I104: =$G$114/(1*8*$K$104) -> 0.625 | J104: m/h | K104: =((E104+E105)/2)/8 -> 2 | M104: 0.5
C105: M.Ajudante | D105: h | E105: 16 | F105: 1 | G105: 12 | H105: =G105*E105*F105 -> 192 | I105: =$G$114/(1*8*$K$104) -> 0.625 | J105: m/h
C106: Betonilha interior/exterior 25 kg cinza Seciltek classic | D106: un | E106: 4 | F106: 1 | G106: 2.59 | H106: =G106*E106*F106 -> 10.36 | I106: 20 | J106: kg/m2/cm
C107: Martelo demolidor 10kg aluguer | D107: dia | E107: 1 | F107: 1 | G107: 25 | H107: =G107*E107*F107 -> 25
C108: Broca martelo | D108: un | E108: 1 | F108: 1 | G108: 4 | H108: =G108*E108*F108 -> 4
C109: Rebardadora + disco | D109: un | E109: 1 | F109: 1 | G109: 4 | H109: =G109*E109*F109 -> 4
C110: Vazadouro | D110: un | E110: 1 | F110: 1 | G110: =200*M104/6 -> 16.666667 | H110: =G110*E110*F110 -> 16.666667
...

Sheet Lista de custos obra
B2: ITEM | C2: DESCRIÇÃO | D2: UN | E2: Quantidade | F2: V.UN | G2: V.TOTAL | H2: Ref. ITEM
B4: MATERIAIS OBRA | G4: =F4*E4 -> 0
G5: =F5*E5 -> 0
G6: =F6*E6 -> 0
G7: =F7*E7 -> 0
G8: =F8*E8 -> 0
G9: =F9*E9 -> 0
G10: =F10*E10 -> 0
G11: =F11*E11 -> 0
G12: =F12*E12 -> 0
G13: =F13*E13 -> 0
G14: =F14*E14 -> 0
G15: =F15*E15 -> 0
G16: =F16*E16 -> 0
... G20: =F20*E20 -> 0
C21: Total | G21: =SUM(G4:G20) -> 0
B23: ITEM | C23: DESCRIÇÃO | D23: UN | E23: Quantidade | F23: V.UN | G23: V.TOTAL | H23: Ref. ITEM
B25: MÃO DE OBRA
C34: Total | G34: =SUM(G25:G33) -> 0
B36: ITEM | C36: DESCRIÇÃO | D36: UN | E36: Quantidade | F36: V.UN | G36: V.TOTAL | H36: Ref. ITEM
B38: DESLOCAÇÕES
C47: Total | G47: =SUM(G38:G46) -> 0
B49: Total | G49: =G21+G34+G47 -> 0

Sheet MQT Real - Analitico
B2: =MQT!B2 -> CO26/0034
B3: =MQT!B3 -> Cliente: Tiago Parada | J3: Analise financeira | P3: =MQT!P3 -> FI Estrutura | R3: =MQT!R3 -> Negociação | S3: =MQT!S3 -> Lucro | T3: =MQT!T3 -> Custo Fixo | U3: =MQT!U3 -> K médio
B4: =MQT!B4 -> Morada: Rua António José de Almeida, 3º Direito, Brandoa, 2650-381 | P4: =MQT!P4 -> 1.15 | R4: =MQT!R4 -> 1 | S4: =MQT!S4 -> 227.43 | T4: =MQT!T4 -> 227.43 | U4: =MQT!U4 -> 1.3
B5: =MQT!B5 -> Responsável: Vinícius Tomaz | P5: =MQT!P5 -> Margem - K
H6: MD05.00 | P6: =MQT!P6 -> Const. civil | Q6: =MQT!Q6 -> Águas | R6: =MQT!R6 -> Gás | S6: =MQT!S6 -> Eletricidade | T6: =MQT!T6 -> AVAC | U6: =MQT!U6 -> SCIE
A7: ITEM | B7: DESCRIÇÃO | C7: UN | D7: QTD | E7: VALOR UNITÁRIO CUSTO | F7: VALOR TOTAL CUSTO | G7: VALOR UNITÁRIO | H7: VALOR TOTAL | J7: Rentabilidade Estimada € | K7: Rentabilidade Estimada % | M7: COMENTÁRIOS | N7: Margem Cap. | P7: =MQT!P7 -> 1.15 | Q7: =MQT!Q7 -> 1.25 | R7: =MQT!R7 -> 1.25 | S7: =MQT!S7 -> 1.25 | T7: =MQT!T7 -> 1.25 | U7: =MQT!U7 -> 1.25
A8: 1 | B8: =MQT!B8 -> Quarto 01 - Crianças | F8: =('Lista de custos obra'!$G$49)*M8 -> #REF! | H8: =SUM(H9:H12) -> #REF! | J8: =SUM(J9:J12) -> #REF! | M8: =H8/$H$68 -> #REF! | N8: =$P$7*R4 -> 1.15
A9: 1.1 | B9: =MQT!B9 -> Solução para tetos interiores, constituída por estrutura com perfis metálicos horizontais F530 afastados a cada 500 mm, suspensos por elementos verticais fixados ao teto, nos quais é fixada 1 camada de placas Gyptec BA13A (STANDARD). Massas, bandas para juntas e acessórios de fixação. Superfícies prontas para acabamento final de pintura ou decoração | G9: =MQT!G9 -> 496.6 | H9: =MQT!H9 -> 496.6 | J9: =H9-F9 -> 496.6 | K9: =(H9/F9)-100% -> #DIV/0!
A10: 1.2 | B10: =MQT!B10 -> Execução de esquema de pintura em teto com Tinta Robbialac 2 em 1 branco, aplicado em 2 demão. Inclui proteção de rodapé, caixilharias, guarnições de portas, utilizando fita multisuperficies, e manga plástica para pavimento | G10: =MQT!G10 -> 278.85 | H10: =MQT!H10 -> 278.85 | J10: =H10-F10 -> 278.85 | K10: =(H10/F10)-100% -> #DIV/0!
A11: 1.3 | B11: =MQT!B11 -> Fornecimento de Sanca HOMESTAR A5 200X3.5X3.5cm em todo perimetro do teto falso. | G11: =MQT!G11 -> 211.523 | H11: =MQT!H11 -> 211.523 | J11: =H11-F11 -> 211.523 | K11: =(H11/F11)-100% -> #DIV/0!
A12: 1.4 | B12: =MQT!#REF! -> #REF! | G12: =MQT!#REF! -> #REF! | H12: =MQT!#REF! -> #REF! | J12: =H12-F12 -> #REF! | K12: =(H12/F12)-100% -> #REF!
A13: 2 | B13: =MQT!B12 -> 0 | F13: =('Lista de custos obra'!$G$49)*M13 -> #REF! | H13: =MQT!H12 -> 984.087 | J13: =SUM(J14:J17) -> 984.087 | M13: =H13/$H$68 -> #REF! | N13: =$P$7*R4 -> 1.15
A14: 2.1 | B14: =MQT!B13 -> Solução para tetos interiores, constituída por estrutura com perfis metálicos horizontais F530 afastados a cada 500 mm, suspensos por elementos verticais fixados ao teto, nos quais é fixada 1 camada de placas Gyptec BA13A (STANDARD). Massas, bandas para juntas e acessórios de fixação. Superfícies prontas para acabamento final de pintura ou decoração | G14: =MQT!G13 -> 496.6 | H14: =MQT!H13 -> 496.6 | J14: =H14-F14 -> 496.6 | K14: =(H14/F14)-100% -> #DIV/0!
A15: 2.2 | B15: =MQT!B14 -> Execução de esquema de pintura em teto com Tinta Robbialac 2 em 1 branco, aplicado em 2 demão. Inclui proteção de rodapé, caixilharias, guarnições de portas, utilizando fita multisuperficies, e manga plástica para pavimento | G15: =MQT!G14 -> 272.35 | H15: =MQT!H14 -> 272.35 | J15: =H15-F15 -> 272.35 | K15: =(H15/F15)-100% -> #DIV/0!
A16: 2.3 | B16: =MQT!B15 -> Fornecimento de Sanca HOMESTAR A5 200X3.5X3.5cm em todo perimetro do teto falso. | G16: =MQT!G15 -> 215.137 | H16: =MQT!H15 -> 215.137 | J16: =H16-F16 -> 215.137 | K16: =(H16/F16)-100% -> #DIV/0!
A17: 2.4 | B17: =MQT!B16 -> 0 | G17: =MQT!G16 -> 0 | H17: =MQT!H16 -> 0 | J17: =H17-F17 -> 0 | K17: =(H17/F17)-100% -> #DIV/0!
A18: 3 | B18: =MQT!B17 -> 0 | F18: =('Lista de custos obra'!$G$49)*M18 -> #REF! | H18: =MQT!H17 -> 0 | J18: =SUM(J19:J22) -> #REF! | M18: =H18/$H$68 -> #REF! | N18: =$P$7*R4 -> 1.15
A19: 3.1 | B19: =MQT!#REF! -> #REF! | G19: =MQT!#REF! -> #REF! | H19: =MQT!#REF! -> #REF! | J19: =H19-F19 -> #REF! | K19: =(H19/F19)-100% -> #REF!
A20: 3.2 | B20: =MQT!#REF! -> #REF! | G20: =MQT!#REF! -> #REF! | H20: =MQT!#REF! -> #REF! | J20: =H20-F20 -> #REF! | K20: =(H20/F20)-100% -> #REF!
A21: 3.3 | B21: =MQT!#REF! -> #REF! | G21: =MQT!#REF! -> #REF! | H21: =MQT!#REF! -> #REF! | J21: =H21-F21 -> #REF! | K21: =(H21/F21)-100% -> #REF!
A22: 3.4 | B22: =MQT!#REF! -> #REF! | G22: =MQT!#REF! -> #REF! | H22: =MQT!#REF! -> #REF! | J22: =H22-F22 -> #REF! | K22: =(H22/F22)-100% -> #REF!
A23: 4 | B23: =MQT!#REF! -> #REF! | F23: =('Lista de custos obra'!$G$49)*M23 -> #REF! | H23: =MQT!#REF! -> #REF! | J23: =SUM(J24:J27) -> #REF! | M23: =H23/$H$68 -> #REF! | N23: =$P$7*R4 -> 1.15
A24: 4.1 | B24: =MQT!#REF! -> #REF! | G24: =MQT!#REF! -> #REF! | H24: =MQT!#REF! -> #REF! | J24: =H24-F24 -> #REF! | K24: =(H24/F24)-100% -> #REF!
A25: 4.2 | B25: =MQT!#REF! -> #REF! | G25: =MQT!#REF! -> #REF! | H25: =MQT!#REF! -> #REF! | J25: =H25-F25 -> #REF! | K25: =(H25/F25)-100% -> #REF!
A26: 4.3 | B26: =MQT!#REF! -> #REF! | G26: =MQT!#REF! -> #REF! | H26: =MQT!#REF! -> #REF! | J26: =H26-F26 -> #REF! | K26: =(H26/F26)-100% -> #REF!
A27: 4.4 | B27: =MQT!#REF! -> #REF! | G27: =MQT!#REF! -> #REF! | H27: =MQT!#REF! -> #REF! | J27: =H27-F27 -> #REF! | K27: =(H27/F27)-100% -> #REF!
A28: 5 | B28: =MQT!#REF! -> #REF! | F28: =('Lista de custos obra'!$G$49)*M28 -> #REF! | H28: =MQT!#REF! -> #REF! | J28: =SUM(J29:J32) -> #REF! | M28: =H28/$H$68 -> #REF! | N28: =$P$7*R4 -> 1.15
A29: 5.1 | B29: =MQT!#REF! -> #REF! | G29: =MQT!#REF! -> #REF! | H29: =MQT!#REF! -> #REF! | J29: =H29-F29 -> #REF! | K29: =(H29/F29)-100% -> #REF!
A30: 5.2 | B30: =MQT!#REF! -> #REF! | G30: =MQT!#REF! -> #REF! | H30: =MQT!#REF! -> #REF! | J30: =H30-F30 -> #REF! | K30: =(H30/F30)-100% -> #REF!
A31: 5.3 | B31: =MQT!#REF! -> #REF! | G31: =MQT!#REF! -> #REF! | H31: =MQT!#REF! -> #REF! | J31: =H31-F31 -> #REF! | K31: =(H31/F31)-100% -> #REF!
A32: 5.4 | B32: =MQT!#REF! -> #REF! | G32: =MQT!#REF! -> #REF! | H32: =MQT!#REF! -> #REF! | J32: =H32-F32 -> #REF! | K32: =(H32/F32)-100% -> #REF!
A33: 6 | B33: =MQT!#REF! -> #REF! | F33: =('Lista de custos obra'!$G$49)*M33 -> #REF! | H33: =MQT!#REF! -> #REF! | J33: =SUM(J34:J37) -> #REF! | M33: =H33/$H$68 -> #REF! | N33: =$P$7*R4 -> 1.15
A34: 6.1 | B34: =MQT!#REF! -> #REF! | G34: =MQT!#REF! -> #REF! | H34: =MQT!#REF! -> #REF! | J34: =H34-F34 -> #REF! | K34: =(H34/F34)-100% -> #REF!
A35: 6.2 | B35: =MQT!#REF! -> #REF! | G35: =MQT!#REF! -> #REF! | H35: =MQT!#REF! -> #REF! | J35: =H35-F35 -> #REF! | K35: =(H35/F35)-100% -> #REF!
A36: 6.3 | B36: =MQT!#REF! -> #REF! | G36: =MQT!#REF! -> #REF! | H36: =MQT!#REF! -> #REF! | J36: =H36-F36 -> #REF! | K36: =(H36/F36)-100% -> #REF!
A37: 6.4 | B37: =MQT!#REF! -> #REF! | G37: =MQT!#REF! -> #REF! | H37: =MQT!#REF! -> #REF! | J37: =H37-F37 -> #REF! | K37: =(H37/F37)-100% -> #REF!
A38: 7 | B38: =MQT!#REF! -> #REF! | F38: =('Lista de custos obra'!$G$49)*M38 -> #REF! | H38: =MQT!#REF! -> #REF! | J38: =SUM(J39:J42) -> #REF! | M38: =H38/$H$68 -> #REF! | N38: =$P$7*R4 -> 1.15
A39: 7.1 | B39: =MQT!#REF! -> #REF! | G39: =MQT!#REF! -> #REF! | H39: =MQT!#REF! -> #REF! | J39: =H39-F39 -> #REF! | K39: =(H39/F39)-100% -> #REF!
A40: 7.2 | B40: =MQT!#REF! -> #REF! | G40: =MQT!#REF! -> #REF! | H40: =MQT!#REF! -> #REF! | J40: =H40-F40 -> #REF! | K40: =(H40/F40)-100% -> #REF!
A41: 7.3 | B41: =MQT!#REF! -> #REF! | G41: =MQT!#REF! -> #REF! | H41: =MQT!#REF! -> #REF! | J41: =H41-F41 -> #REF! | K41: =(H41/F41)-100% -> #REF!
A42: 7.4 | B42: =MQT!#REF! -> #REF! | G42: =MQT!#REF! -> #REF! | H42: =MQT!#REF! -> #REF! | J42: =H42-F42 -> #REF! | K42: =(H42/F42)-100% -> #REF!
A43: 8 | B43: =MQT!#REF! -> #REF! | F43: =('Lista de custos obra'!$G$49)*M43 -> #REF! | H43: =MQT!#REF! -> #REF! | J43: =SUM(J44:J47) -> #REF! | M43: =H43/$H$68 -> #REF! | N43: =$P$7*R4 -> 1.15
A44: 8.1 | B44: =MQT!#REF! -> #REF! | G44: =MQT!#REF! -> #REF! | H44: =MQT!#REF! -> #REF! | J44: =H44-F44 -> #REF! | K44: =(H44/F44)-100% -> #REF!
A45: 8.2 | B45: =MQT!#REF! -> #REF! | G45: =MQT!#REF! -> #REF! | H45: =MQT!#REF! -> #REF! | J45: =H45-F45 -> #REF! | K45: =(H45/F45)-100% -> #REF!
A46: 8.3 | B46: =MQT!#REF! -> #REF! | G46: =MQT!#REF! -> #REF! | H46: =MQT!#REF! -> #REF! | J46: =H46-F46 -> #REF! | K46: =(H46/F46)-100% -> #REF!
A47: 8.4 | B47: =MQT!#REF! -> #REF! | G47: =MQT!#REF! -> #REF! | H47: =MQT!#REF! -> #REF! | J47: =H47-F47 -> #REF! | K47: =(H47/F47)-100% -> #REF!
A48: 9 | B48: =MQT!#REF! -> #REF! | F48: =('Lista de custos obra'!$G$49)*M48 -> #REF! | H48: =MQT!#REF! -> #REF! | J48: =SUM(J49:J52) -> #REF! | M48: =H48/$H$68 -> #REF! | N48: =$P$7*R4 -> 1.15
A49: 9.1 | B49: =MQT!#REF! -> #REF! | G49: =MQT!#REF! -> #REF! | H49: =MQT!#REF! -> #REF! | J49: =H49-F49 -> #REF! | K49: =(H49/F49)-100% -> #REF!
A50: 9.2 | B50: =MQT!#REF! -> #REF! | G50: =MQT!#REF! -> #REF! | H50: =MQT!#REF! -> #REF! | J50: =H50-F50 -> #REF! | K50: =(H50/F50)-100% -> #REF!
A51: 9.3 | B51: =MQT!#REF! -> #REF! | G51: =MQT!#REF! -> #REF! | H51: =MQT!#REF! -> #REF! | J51: =H51-F51 -> #REF! | K51: =(H51/F51)-100% -> #REF!
A52: 9.4 | B52: =MQT!#REF! -> #REF! | G52: =MQT!#REF! -> #REF! | H52: =MQT!#REF! -> #REF! | J52: =H52-F52 -> #REF! | K52: =(H52/F52)-100% -> #REF!
A53: 10 | B53: =MQT!#REF! -> #REF! | F53: =('Lista de custos obra'!$G$49)*M53 -> #REF! | H53: =MQT!#REF! -> #REF! | J53: =SUM(J54:J57) -> #REF! | M53: =H53/$H$68 -> #REF! | N53: =$P$7*R4 -> 1.15
A54: 10.1 | B54: =MQT!#REF! -> #REF! | G54: =MQT!#REF! -> #REF! | H54: =MQT!#REF! -> #REF! | J54: =H54-F54 -> #REF! | K54: =(H54/F54)-100% -> #REF!
A55: 10.2 | B55: =MQT!#REF! -> #REF! | G55: =MQT!#REF! -> #REF! | H55: =MQT!#REF! -> #REF! | J55: =H55-F55 -> #REF! | K55: =(H55/F55)-100% -> #REF!
A56: 10.3 | B56: =MQT!#REF! -> #REF! | G56: =MQT!#REF! -> #REF! | H56: =MQT!#REF! -> #REF! | J56: =H56-F56 -> #REF! | K56: =(H56/F56)-100% -> #REF!
A57: 10.4 | B57: =MQT!#REF! -> #REF! | G57: =MQT!#REF! -> #REF! | H57: =MQT!#REF! -> #REF! | J57: =H57-F57 -> #REF! | K57: =(H57/F57)-100% -> #REF!
A60: Notas: | J60: Imposto sobre orçamento
A61: 1 - | B61: A proposta só é válida em sua globalidade, reservando a empresa o direito de rever os valores em caso de adjudicação parcial. | J61: =H68 -> #REF! | K61: IVA | L61: 0.23 | M61: =J61*L61 -> #REF!
A62: 2 - | B62: Todos os trabalhos foram considerados em horário normal. | J62: =H68 -> #REF! | K62: IVA | L62: 0.06 | M62: =L62*J62 -> #REF!
A63: 3 - | B63: Condições de pagamento: 50% na adjudicação a P.P., 30% a meio da obra a P.P. e, 20% nos términos dos trabalhos a P.P. *P.P. (Pronto pagamento) | J63: Total a Faturar | M63: =M62+J62 -> #REF!
A64: 4 - | B64: Os valores apresentados nas propostas estão sujeitos ao Imposto sobre o Valor Acrescentado (IVA), aplicado à taxa legal em vigor. | J64: Condições de pagamento
A65: 5 - | J65: 1º Fatura | K65: 0.3 | M65: =K65*M63 -> #REF!
J66: 2º Fatura | K66: 0.3 | M66: =K66*M63 -> #REF!
F67: TOTAL CUSTO | H67: TOTAL PROPOSTA | J67: 3º Fatura | K67: 0.4 | M67: =K67*M63 -> #REF!
F68: =F8+F13+F18+F23+F28+F33+F38+F43+F48+F53 -> #REF! | H68: =SUM(H18,H13,H8,H23,H28,H33,H38,H43,H48,H53) -> #REF!
J69: LUCRO ESTIMADO
J70: =SUM(J18,J13,J8,J23,J28,J33,J38,J43,J48,J53) -> #REF!

Sheet Lista de composição de testes
B3: ITEM | C3: DESCRIÇÃO | D3: UN | E3: QTD | G3: V.UN | H3: V.TOTAL S/Margem | I3: V.TOTAL C/Margem 1,3
E4: Qtd padrão | F4: Qtd pontual
B5: Relatório Técnico | C5: Eng. Civil | D5: h | E5: 4 | F5: 1 | G5: 25 | H5: =G5*E5 -> 100 | I5: =G5*E5*1.6 -> 160
C6: Transporte | D6: un | E6: 1 | F6: 1 | G6: 20 | H6: =G6*E6 -> 20 | I6: =G6*E6*2 -> 40
C7: Acessórios
C8: Total | H8: =SUM(H5:H7) -> 120 | I8: =SUM(I5:I7) -> 200
C9: Total/m2 | E9: Área | G9: 1 | H9: =ROUNDUP((H8/G9),0) -> 120 | I9: =ROUNDUP((I8/G9),0) -> 200
B11: ITEM | C11: DESCRIÇÃO | D11: UN | E11: QTD | G11: V.UN | H11: V.TOTAL S/Margem | I11: V.TOTAL C/Margem
E12: Qtd padrão | F12: Qtd pontual
B13: Teste Corantes | C13: Técnico | D13: h | E13: 1 | F13: 1 | G13: 25 | H13: =G13*E13 -> 25 | I13: =G13*E13*1.3 -> 32.5
C14: Material | D14: un | E14: 1 | F14: 1 | G14: 5 | H14: =G14*E14 -> 5 | I14: =G14*E14*1.35 -> 6.75
C15: Acessórios
C16: Total | H16: =SUM(H13:H15) -> 30 | I16: =SUM(I13:I15) -> 39.25
C17: Total/m2 | E17: Área | G17: 1 | H17: =ROUNDUP((H16/G17),0) -> 30 | I17: =ROUNDUP((I16/G17),0) -> 40
B19: ITEM | C19: DESCRIÇÃO | D19: UN | E19: QTD | G19: V.UN | H19: V.TOTAL S/Margem | I19: V.TOTAL C/Margem
E20: Qtd padrão | F20: Qtd pontual
B21: Teste de pressão | C21: Técnico | D21: h | E21: 1 | F21: 1 | G21: 25 | H21: =G21*E21 -> 25 | I21: =G21*E21*1.3 -> 32.5
C22: Material | D22: un | E22: 1 | F22: 1 | G22: 5 | H22: =G22*E22 -> 5 | I22: =G22*E22*1.35 -> 6.75
C23: Acessórios
C24: Total | H24: =SUM(H21:H23) -> 30 | I24: =SUM(I21:I23) -> 39.25
C25: Total/m2 | E25: Área | G25: 1 | H25: =ROUNDUP((H24/G25),0) -> 30 | I25: =ROUNDUP((I24/G25),0) -> 40
B27: ITEM | C27: DESCRIÇÃO | D27: UN | E27: QTD | G27: V.UN | H27: V.TOTAL S/Margem | I27: V.TOTAL C/Margem
E28: Qtd padrão | F28: Qtd pontual
B29: Teste de obturação | C29: Técnico | D29: h | E29: 1 | F29: 1 | G29: 25 | H29: =G29*E29 -> 25 | I29: =G29*E29*1.3 -> 32.5
C30: Material | D30: un | E30: 1 | F30: 1 | G30: 5 | H30: =G30*E30 -> 5 | I30: =G30*E30*1.35 -> 6.75
C31: Acessórios
C32: Total | H32: =SUM(H29:H31) -> 30 | I32: =SUM(I29:I31) -> 39.25
C33: Total/m2 | E33: Área | G33: 1 | H33: =ROUNDUP((H32/G33),0) -> 30 | I33: =ROUNDUP((I32/G33),0) -> 40
B35: ITEM | C35: DESCRIÇÃO | D35: UN | E35: QTD | G35: V.UN | H35: V.TOTAL S/Margem | I35: V.TOTAL C/Margem
E36: Qtd padrão | F36: Qtd pontual
B37: Teste com termografia | C37: Técnico | D37: h | E37: 1 | F37: 1 | G37: 25 | H37: =G37*E37 -> 25 | I37: =G37*E37*1.3 -> 32.5
C38: Material | D38: un | E38: 1 | F38: 1 | G38: 5 | H38: =G38*E38 -> 5 | I38: =G38*E38*1.35 -> 6.75
C39: Acessórios
C40: Total | H40: =SUM(H37:H39) -> 30 | I40: =SUM(I37:I39) -> 39.25
C41: Total/m2 | E41: Área | G41: 1 | H41: =ROUNDUP((H40/G41),0) -> 30 | I41: =ROUNDUP((I40/G41),0) -> 40
B43: ITEM | C43: DESCRIÇÃO | D43: UN | E43: QTD | G43: V.UN | H43: V.TOTAL S/Margem | I43: V.TOTAL C/Margem
E44: Qtd padrão | F44: Qtd pontual
B45: Deslocação | C45: Deslocação | D45: un | E45: 1 | F45: 1 | G45: 25.015 | H45: =G45*E45 -> 25.015 | I45: =G45*E45*1.58 -> 39.5237
C46: Deslocação fora lisboa | D46: km | E46: 1 | F46: 1 | G46: 0.4 | H46: =G46*E46 -> 0.4 | I46: -
C47: Acessórios
C48: Total | H48: =SUM(H45) -> 25.015 | I48: =SUM(I45) -> 39.5237
C49: Total/m2 | E49: Área | G49: 1 | H49: =ROUNDUP((H48/G49),0) -> 26 | I49: =ROUNDUP((I48/G49),0) -> 40

Sheet Lista de composição TB pontuais
B2: ITEM | C2: DESCRIÇÃO | D2: UN | E2: QTD | F2: V.UN | G2: V.TOTAL | H2: K | I2: V.UN - Venda | J2: V.TOTAL - Venda | K2: IVA 23% | M2: Rentabilidade Estimada € | N2: Rentabilidade Estimada %
B4: Reparação de rotura em tubo multicamada Ø20mm, incluindo remoção de cerâmico, abertura de roço, fecho com argamassa de reboco, fornecimento e aplicação de cerâmica similar a existente, incluindo todos os trabalhos necessários para excelente acabamento. | C4: Canalização | G4: =SUM(G5:G12) -> 0
C5: Desmontagem (loiças) | D5: un | F5: 50 | G5: =F5*E5 -> 0 | H5: 1.45 | I5: =F5*$H$5 -> 72.5 | J5: =I5*E5 -> 0 | K5: =J5*1.23 -> 0 | M5: =J5-G5 -> 0 | N5: =(J5/G5)-100% -> #DIV/0!
C6: Remoção de cerâmicos | D6: m2 | F6: 15 | G6: =F6*E6 -> 0 | I6: =F6*$H$5 -> 21.75 | J6: =I6*E6 -> 0 | K6: =J6*1.23 -> 0 | M6: =J6-G6 -> 0 | N6: =(J6/G6)-100% -> #DIV/0!
C7: Abertura de roços | D7: m | F7: 28.5 | G7: =F7*E7 -> 0 | I7: =F7*$H$5 -> 41.325 | J7: =I7*E7 -> 0 | K7: =J7*1.23 -> 0 | M7: =J7-G7 -> 0 | N7: =(J7/G7)-100% -> #DIV/0!
C8: Fornecimento e aplicação de tubo multicamada 20mm | D8: m | F8: 38 | G8: =F8*E8 -> 0 | I8: =F8*$H$5 -> 55.1 | J8: =I8*E8 -> 0 | K8: =J8*1.23 -> 0 | M8: =J8-G8 -> 0 | N8: =(J8/G8)-100% -> #DIV/0!
C9: Oficial de Canalizador | D9: h | F9: 17 | G9: =F9*E9 -> 0 | I9: =F9*$H$5 -> 24.65 | J9: =I9*E9 -> 0 | K9: =J9*1.23 -> 0 | M9: =J9-G9 -> 0 | N9: =(J9/G9)-100% -> #DIV/0!
C10: Ajudante de predeiro | D10: h | F10: 12 | G10: =F10*E10 -> 0 | I10: =F10*$H$5 -> 17.4 | J10: =I10*E10 -> 0 | K10: =J10*1.23 -> 0 | M10: =J10-G10 -> 0 | N10: =(J10/G10)-100% -> #DIV/0!
C11: Depósito de resíduos a vazadouro | D11: un | F11: 20 | G11: =F11*E11 -> 0 | I11: =F11*$H$5 -> 29 | J11: =I11*E11 -> 0 | K11: =J11*1.23 -> 0 | M11: =J11-G11 -> 0 | N11: =(J11/G11)-100% -> #DIV/0!
C12: Deslocação | D12: un | F12: 20 | G12: =F12*E12 -> 0 | I12: =F12*$H$5 -> 29 | J12: =I12*E12 -> 0 | K12: =J12*1.23 -> 0 | M12: =J12-G12 -> 0 | N12: =(J12/G12)-100% -> #DIV/0!
C13: Construção civil | G13: =SUM(G14:G24) -> 0
C14: Oficial Pedreiro | D14: h | F14: 17 | G14: =F14*E14 -> 0 | I14: =F14*$H$5 -> 24.65 | J14: =I14*E14 -> 0 | K14: =J14*1.23 -> 0 | M14: =J14-G14 -> 0 | N14: =(J14/G14)-100% -> #DIV/0!
C15: Ajudante de pedreiro | D15: h | F15: 12 | G15: =F15*E15 -> 0 | I15: =F15*$H$5 -> 17.4 | J15: =I15*E15 -> 0 | K15: =J15*1.23 -> 0 | M15: =J15-G15 -> 0 | N15: =(J15/G15)-100% -> #DIV/0!
C16: Fecho de roços com argamassa | D16: m | F16: 28.5 | G16: =F16*E16 -> 0 | I16: =F16*$H$5 -> 41.325 | J16: =I16*E16 -> 0 | K16: =J16*1.23 -> 0 | M16: =J16-G16 -> 0 | N16: =(J16/G16)-100% -> #DIV/0!
C17: Regularização de paredes | D17: m2 | F17: 12 | G17: =F17*E17 -> 0 | I17: =F17*$H$5 -> 17.4 | J17: =I17*E17 -> 0 | K17: =J17*1.23 -> 0 | M17: =J17-G17 -> 0 | N17: =(J17/G17)-100% -> #DIV/0!
C18: Fornecimento e aplicação de cerâmico | D18: m2 | F18: 40 | G18: =F18*E18 -> 0 | I18: =F18*$H$5 -> 58 | J18: =I18*E18 -> 0 | K18: =J18*1.23 -> 0 | M18: =J18-G18 -> 0 | N18: =(J18/G18)-100% -> #DIV/0!
C19: Montagem (loiças) | D19: un | F19: 50 | G19: =F19*E19 -> 0 | I19: =F19*$H$5 -> 72.5 | J19: =I19*E19 -> 0 | K19: =J19*1.23 -> 0 | M19: =J19-G19 -> 0 | N19: =(J19/G19)-100% -> #DIV/0!
C20: Trabalhos de movimentação e proteção de móveis | D20: h | F20: 12 | G20: =F20*E20 -> 0 | I20: =F20*$H$5 -> 17.4 | J20: =I20*E20 -> 0 | K20: =J20*1.23 -> 0 | M20: =J20-G20 -> 0 | N20: =(J20/G20)-100% -> #DIV/0!
C21: Trabalhos preparatórios de obra | D21: h | F21: 12 | G21: =F21*E21 -> 0 | I21: =F21*$H$5 -> 17.4 | J21: =I21*E21 -> 0 | K21: =J21*1.23 -> 0 | M21: =J21-G21 -> 0 | N21: =(J21/G21)-100% -> #DIV/0!
C22: Depósito de resíduos a vazadouro | D22: un | F22: 20 | G22: =F22*E22 -> 0 | I22: =F22*$H$5 -> 29 | J22: =I22*E22 -> 0 | K22: =J22*1.23 -> 0 | M22: =J22-G22 -> 0 | N22: =(J22/G22)-100% -> #DIV/0!
C23: Limpeza de obra | D23: un | F23: 20 | G23: =F23*E23 -> 0 | I23: =F23*$H$5 -> 29 | J23: =I23*E23 -> 0 | K23: =J23*1.23 -> 0 | M23: =J23-G23 -> 0 | N23: =(J23/G23)-100% -> #DIV/0!
C24: Deslocação | D24: un | F24: 20 | G24: =F24*E24 -> 0 | I24: =F24*$H$5 -> 29 | J24: =I24*E24 -> 0 | K24: =J24*1.23 -> 0 | M24: =J24-G24 -> 0 | N24: =(J24/G24)-100% -> #DIV/0!
C25: Total | G25: =SUM(G5:G12,G14:G24) -> 0 | I25: Total | J25: =SUM(J5:J24) -> 0 | K25: =SUM(K5:K24) -> 0 | M25: =SUM(M5:M24) -> 0
C26: Total/vg | E26: valor global | F26: 1 | G26: =ROUNDUP((G25/F26),0) -> 0
B28: ITEM | C28: DESCRIÇÃO | D28: UN | E28: QTD | F28: V.UN | G28: V.TOTAL | H28: K | I28: V.UN - Venda | J28: V.TOTAL - Venda | K28: IVA 23% | M28: Rentabilidade Estimada € | N28: Rentabilidade Estimada %
B30: Reparação de rotura em tubo multicamada Ø20mm, incluindo abertura de roço, fecho com argamassa de reboco, preparação de superficie com massa de estuque, execução de pintura com primário e tinta plástica, incluindo todos os trabalhos necessários para excelente acabamento. | C30: Canalização | G30: =SUM(G31:G36) -> 0
C31: Abertura de roços | D31: m | F31: 28.5 | G31: =F31*E31 -> 0 | H31: 1.45 | I31: =F31*$H$31 -> 41.325 | J31: =I31*E31 -> 0 | K31: =J31*1.23 -> 0 | M31: =J31-G31 -> 0 | N31: =(J31/G31)-100% -> #DIV/0!
C32: Fornecimento e aplicação de tubo multicamada 20mm | D32: m | F32: 38 | G32: =F32*E32 -> 0 | I32: =F32*$H$31 -> 55.1 | J32: =I32*E32 -> 0 | K32: =J32*1.23 -> 0 | M32: =J32-G32 -> 0 | N32: =(J32/G32)-100% -> #DIV/0!
C33: Oficial de Canalizador | D33: h | F33: 17 | G33: =F33*E33 -> 0 | I33: =F33*$H$31 -> 24.65 | J33: =I33*E33 -> 0 | K33: =J33*1.23 -> 0 | M33: =J33-G33 -> 0 | N33: =(J33/G33)-100% -> #DIV/0!
C34: Ajudante de canalizador | D34: h | F34: 12 | G34: =F34*E34 -> 0 | I34: =F34*$H$31 -> 17.4 | J34: =I34*E34 -> 0 | K34: =J34*1.23 -> 0 | M34: =J34-G34 -> 0 | N34: =(J34/G34)-100% -> #DIV/0!
C35: Depósito de resíduos a vazadouro | D35: un | F35: 20 | G35: =F35*E35 -> 0 | I35: =F35*$H$31 -> 29 | J35: =I35*E35 -> 0 | K35: =J35*1.23 -> 0 | M35: =J35-G35 -> 0 | N35: =(J35/G35)-100% -> #DIV/0!
C36: Deslocação | D36: un | F36: 20 | G36: =F36*E36 -> 0 | I36: =F36*$H$31 -> 29 | J36: =I36*E36 -> 0 | K36: =J36*1.23 -> 0 | M36: =J36-G36 -> 0 | N36: =(J36/G36)-100% -> #DIV/0!
C37: Construção civil | G37: =SUM(G38:G50) -> 0
C38: Oficial Pedreiro | D38: h | F38: 17 | G38: =F38*E38 -> 0 | I38: =F38*$H$31 -> 24.65 | J38: =I38*E38 -> 0 | K38: =J38*1.23 -> 0 | M38: =J38-G38 -> 0 | N38: =(J38/G38)-100% -> #DIV/0!
C39: Ajudante de pedreiro | D39: h | F39: 12 | G39: =F39*E39 -> 0 | I39: =F39*$H$31 -> 17.4 | J39: =I39*E39 -> 0 | K39: =J39*1.23 -> 0 | M39: =J39-G39 -> 0 | N39: =(J39/G39)-100% -> #DIV/0!
C40: Fecho de roços com argamassa | D40: m | F40: 28.5 | G40: =F40*E40 -> 0 | I40: =F40*$H$31 -> 41.325 | J40: =I40*E40 -> 0 | K40: =J40*1.23 -> 0 | M40: =J40-G40 -> 0 | N40: =(J40/G40)-100% -> #DIV/0!
C41: Execução de reboco para estuque | D41: m2 | F41: 13 | G41: =F41*E41 -> 0 | I41: =F41*$H$31 -> 18.85 | J41: =I41*E41 -> 0 | K41: =J41*1.23 -> 0 | M41: =J41-G41 -> 0 | N41: =(J41/G41)-100% -> #DIV/0!
C42: Execução de estuque em paredes | D42: m2 | F42: 15 | G42: =F42*E42 -> 0 | I42: =F42*$H$31 -> 21.75 | J42: =I42*E42 -> 0 | K42: =J42*1.23 -> 0 | M42: =J42-G42 -> 0 | N42: =(J42/G42)-100% -> #DIV/0!
C43: Preparação de superficies (lixar/emassar) | D43: m2 | F43: 10 | G43: =F43*E43 -> 0 | I43: =F43*$H$31 -> 14.5 | J43: =I43*E43 -> 0 | K43: =J43*1.23 -> 0 | M43: =J43-G43 -> 0 | N43: =(J43/G43)-100% -> #DIV/0!
C44: Fornecimento e aplicação de primário | D44: m2 | F44: 6 | G44: =F44*E44 -> 0 | I44: =F44*$H$31 -> 8.7 | J44: =I44*E44 -> 0 | K44: =J44*1.23 -> 0 | M44: =J44-G44 -> 0 | N44: =(J44/G44)-100% -> #DIV/0!
C45: Pintura de paredes | D45: m2 | F45: 8 | G45: =F45*E45 -> 0 | I45: =F45*$H$31 -> 11.6 | J45: =I45*E45 -> 0 | K45: =J45*1.23 -> 0 | M45: =J45-G45 -> 0 | N45: =(J45/G45)-100% -> #DIV/0!
C46: Trabalhos de movimentação e proteção de móveis | D46: h | F46: 12 | G46: =F46*E46 -> 0 | I46: =F46*$H$31 -> 17.4 | J46: =I46*E46 -> 0 | K46: =J46*1.23 -> 0 | M46: =J46-G46 -> 0 | N46: =(J46/G46)-100% -> #DIV/0!
C47: Trabalhos preparatórios de obra | D47: h | F47: 12 | G47: =F47*E47 -> 0 | I47: =F47*$H$31 -> 17.4 | J47: =I47*E47 -> 0 | K47: =J47*1.23 -> 0 | M47: =J47-G47 -> 0 | N47: =(J47/G47)-100% -> #DIV/0!
C48: Depósito de resíduos a vazadouro | D48: un | F48: 20 | G48: =F48*E48 -> 0 | I48: =F48*$H$31 -> 29 | J48: =I48*E48 -> 0 | K48: =J48*1.23 -> 0 | M48: =J48-G48 -> 0 | N48: =(J48/G48)-100% -> #DIV/0!
C49: Limpeza de obra | D49: un | F49: 20 | G49: =F49*E49 -> 0 | I49: =F49*$H$31 -> 29 | J49: =I49*E49 -> 0 | K49: =J49*1.23 -> 0 | M49: =J49-G49 -> 0 | N49: =(J49/G49)-100% -> #DIV/0!
C50: Deslocação | D50: un | F50: 20 | G50: =F50*E50 -> 0 | I50: =F50*$H$31 -> 29 | J50: =I50*E50 -> 0 | K50: =J50*1.23 -> 0 | M50: =J50-G50 -> 0 | N50: =(J50/G50)-100% -> #DIV/0!
C51: Total | G51: =SUM(G31:G36,G38:G50) -> 0 | I51: Total | J51: =SUM(J31:J50) -> 0 | K51: =SUM(K31:K50) -> 0 | M51: =SUM(M31:M50) -> 0
C52: Total/vg | E52: valor global | F52: 1 | G52: =ROUNDUP((G51/F52),0) -> 0
B54: ITEM | C54: DESCRIÇÃO | D54: UN | E54: QTD | F54: V.UN | G54: V.TOTAL | H54: K | I54: V.UN - Venda | J54: V.TOTAL - Venda | K54: IVA 23% | M54: Rentabilidade Estimada € | N54: Rentabilidade Estimada %
B56: Reparação de rotura em tubo de esgoto sanita, incluindo remoção de cerâmico, abertura de roço, fecho com argamassa de reboco, fornecimento e aplicação de cerâmica similar a existente, incluindo todos os trabalhos necessários para excelente acabamento. | C56: Canalização | G56: =SUM(G57:G66) -> 0
C57: Desmontagem (loiças) | D57: un | F57: 50 | G57: =F57*E57 -> 0 | H57: 1.45 | I57: =F57*$H$57 -> 72.5 | J57: =I57*E57 -> 0 | K57: =J57*1.23 -> 0 | M57: =J57-G57 -> 0 | N57: =(J57/G57)-100% -> #DIV/0!
C58: Remoção de cerâmicos | D58: m2 | F58: 15 | G58: =F58*E58 -> 0 | I58: =F58*$H$57 -> 21.75 | J58: =I58*E58 -> 0 | K58: =J58*1.23 -> 0 | M58: =J58-G58 -> 0 | N58: =(J58/G58)-100% -> #DIV/0!
C59: Abertura de roços | D59: m | F59: 28.5 | G59: =F59*E59 -> 0 | I59: =F59*$H$57 -> 41.325 | J59: =I59*E59 -> 0 | K59: =J59*1.23 -> 0 | M59: =J59-G59 -> 0 | N59: =(J59/G59)-100% -> #DIV/0!
C60: Execução de esgotos com tubo diâmetro 40 | D60: m | F60: 50 | G60: =F60*E60 -> 0 | I60: =F60*$H$57 -> 72.5 | J60: =I60*E60 -> 0 | K60: =J60*1.23 -> 0 | M60: =J60-G60 -> 0 | N60: =(J60/G60)-100% -> #DIV/0!
C61: Fornecimento e aplicação de sifão de pavimento | D61: un | F61: 50 | G61: =F61*E61 -> 0 | I61: =F61*$H$57 -> 72.5 | J61: =I61*E61 -> 0 | K61: =J61*1.23 -> 0 | M61: =J61-G61 -> 0 | N61: =(J61/G61)-100% -> #DIV/0!
C62: Execução de novo canhão de sanita e ligações à prumada tubo 90 | D62: un | F62: 150 | G62: =F62*E62 -> 0 | I62: =F62*$H$57 -> 217.5 | J62: =I62*E62 -> 0 | K62: =J62*1.23 -> 0 | M62: =J62-G62 -> 0 | N62: =(J62/G62)-100% -> #DIV/0!
C63: Oficial de Canalizador | D63: h | F63: 17 | G63: =F63*E63 -> 0 | I63: =F63*$H$57 -> 24.65 | J63: =I63*E63 -> 0 | K63: =J63*1.23 -> 0 | M63: =J63-G63 -> 0 | N63: =(J63/G63)-100% -> #DIV/0!
C64: Ajudante de predeiro | D64: h | F64: 12 | G64: =F64*E64 -> 0 | I64: =F64*$H$57 -> 17.4 | J64: =I64*E64 -> 0 | K64: =J64*1.23 -> 0 | M64: =J64-G64 -> 0 | N64: =(J64/G64)-100% -> #DIV/0!
C65: Depósito de resíduos a vazadouro | D65: un | F65: 20 | G65: =F65*E65 -> 0 | I65: =F65*$H$57 -> 29 | J65: =I65*E65 -> 0 | K65: =J65*1.23 -> 0 | M65: =J65-G65 -> 0 | N65: =(J65/G65)-100% -> #DIV/0!
C66: Deslocação | D66: un | F66: 20 | G66: =F66*E66 -> 0 | I66: =F66*$H$57 -> 29 | J66: =I66*E66 -> 0 | K66: =J66*1.23 -> 0 | M66: =J66-G66 -> 0 | N66: =(J66/G66)-100% -> #DIV/0!
C67: Construção civil | G67: =SUM(G68:G78) -> 0
C68: Oficial Pedreiro | D68: h | F68: 17 | G68: =F68*E68 -> 0 | I68: =F68*$H$57 -> 24.65 | J68: =I68*E68 -> 0 | K68: =J68*1.23 -> 0 | M68: =J68-G68 -> 0 | N68: =(J68/G68)-100% -> #DIV/0!
C69: Ajudante de pedreiro | D69: h | F69: 12 | G69: =F69*E69 -> 0 | I69: =F69*$H$57 -> 17.4 | J69: =I69*E69 -> 0 | K69: =J69*1.23 -> 0 | M69: =J69-G69 -> 0 | N69: =(J69/G69)-100% -> #DIV/0!
C70: Fecho de roços com argamassa | D70: m | F70: 28.5 | G70: =F70*E70 -> 0 | I70: =F70*$H$57 -> 41.325 | J70: =I70*E70 -> 0 | K70: =J70*1.23 -> 0 | M70: =J70-G70 -> 0 | N70: =(J70/G70)-100% -> #DIV/0!
C71: Regularização de paredes | D71: m2 | F71: 12 | G71: =F71*E71 -> 0 | I71: =F71*$H$57 -> 17.4 | J71: =I71*E71 -> 0 | K71: =J71*1.23 -> 0 | M71: =J71-G71 -> 0 | N71: =(J71/G71)-100% -> #DIV/0!
C72: Fornecimento e aplicação de cerâmico | D72: m2 | F72: 40 | G72: =F72*E72 -> 0 | I72: =F72*$H$57 -> 58 | J72: =I72*E72 -> 0 | K72: =J72*1.23 -> 0 | M72: =J72-G72 -> 0 | N72: =(J72/G72)-100% -> #DIV/0!
C73: Montagem (loiças) | D73: un | F73: 50 | G73: =F73*E73 -> 0 | I73: =F73*$H$57 -> 72.5 | J73: =I73*E73 -> 0 | K73: =J73*1.23 -> 0 | M73: =J73-G73 -> 0 | N73: =(J73/G73)-100% -> #DIV/0!
C74: Trabalhos de movimentação e proteção de móveis | D74: h | F74: 12 | G74: =F74*E74 -> 0 | I74: =F74*$H$57 -> 17.4 | J74: =I74*E74 -> 0 | K74: =J74*1.23 -> 0 | M74: =J74-G74 -> 0 | N74: =(J74/G74)-100% -> #DIV/0!
C75: Trabalhos preparatórios de obra | D75: h | F75: 12 | G75: =F75*E75 -> 0 | I75: =F75*$H$57 -> 17.4 | J75: =I75*E75 -> 0 | K75: =J75*1.23 -> 0 | M75: =J75-G75 -> 0 | N75: =(J75/G75)-100% -> #DIV/0!
C76: Depósito de resíduos a vazadouro | D76: un | F76: 20 | G76: =F76*E76 -> 0 | I76: =F76*$H$57 -> 29 | J76: =I76*E76 -> 0 | K76: =J76*1.23 -> 0 | M76: =J76-G76 -> 0 | N76: =(J76/G76)-100% -> #DIV/0!
C77: Limpeza de obra | D77: un | F77: 20 | G77: =F77*E77 -> 0 | I77: =F77*$H$57 -> 29 | J77: =I77*E77 -> 0 | K77: =J77*1.23 -> 0 | M77: =J77-G77 -> 0 | N77: =(J77/G77)-100% -> #DIV/0!
C78: Deslocação | D78: un | F78: 20 | G78: =F78*E78 -> 0 | I78: =F78*$H$57 -> 29 | J78: =I78*E78 -> 0 | K78: =J78*1.23 -> 0 | M78: =J78-G78 -> 0 | N78: =(J78/G78)-100% -> #DIV/0!
C79: Total | G79: =SUM(G57:G66,G68:G78) -> 0 | I79: Total | J79: =SUM(J57:J78) -> 0 | K79: =SUM(K57:K78) -> 0 | M79: =SUM(M57:M78) -> 0
C80: Total/vg | E80: valor global | F80: 1 | G80: =ROUNDUP((G79/F80),0) -> 0
B82: ITEM | C82: DESCRIÇÃO | D82: UN | E82: QTD | F82: V.UN | G82: V.TOTAL | H82: K | I82: V.UN - Venda | J82: V.TOTAL - Venda | K82: IVA 23% | M82: Rentabilidade Estimada € | N82: Rentabilidade Estimada %
B84: Substituição de válvula de banheira com instalação de grelha de ventilação, incluindo todos os trabalhos necessários para excelente acabamento. | C84: Canalização | G84: =SUM(G85:G94) -> 0
C85: Desmontagem (loiças) | D85: un | F85: 50 | G85: =F85*E85 -> 0 | H85: 1.45 | I85: =F85*$H$85 -> 72.5 | J85: =I85*E85 -> 0 | K85: =J85*1.23 -> 0 | M85: =J85-G85 -> 0 | N85: =(J85/G85)-100% -> #DIV/0!
C86: Remoção de cerâmicos | D86: m2 | F86: 15 | G86: =F86*E86 -> 0 | I86: =F86*$H$85 -> 21.75 | J86: =I86*E86 -> 0 | K86: =J86*1.23 -> 0 | M86: =J86-G86 -> 0 | N86: =(J86/G86)-100% -> #DIV/0!
C87: Abertura de janela no mureto da banheira | D87: m2 | F87: 20 | G87: =F87*E87 -> 0 | I87: =F87*$H$85 -> 29 | J87: =I87*E87 -> 0 | K87: =J87*1.23 -> 0 | M87: =J87-G87 -> 0 | N87: =(J87/G87)-100% -> #DIV/0!
C88: Fornecimento e aplicação de válvula de banheira | D88: un | F88: 50 | G88: =F88*E88 -> 0 | I88: =F88*$H$85 -> 72.5 | J88: =I88*E88 -> 0 | K88: =J88*1.23 -> 0 | M88: =J88-G88 -> 0 | N88: =(J88/G88)-100% -> #DIV/0!
C89: Fornecimento e aplicação de tubo PVC 40" | D89: m2 | F89: 50 | G89: =F89*E89 -> 0 | I89: =F89*$H$85 -> 72.5 | J89: =I89*E89 -> 0 | K89: =J89*1.23 -> 0 | M89: =J89-G89 -> 0 | N89: =(J89/G89)-100% -> #DIV/0!
C90: Fornecimento e aplicação de grelha no mureto da banheira | D90: un | F90: 30 | G90: =F90*E90 -> 0 | I90: =F90*$H$85 -> 43.5 | J90: =I90*E90 -> 0 | K90: =J90*1.23 -> 0 | M90: =J90-G90 -> 0 | N90: =(J90/G90)-100% -> #DIV/0!
C91: Oficial de Canalizador | D91: h | F91: 17 | G91: =F91*E91 -> 0 | I91: =F91*$H$85 -> 24.65 | J91: =I91*E91 -> 0 | K91: =J91*1.23 -> 0 | M91: =J91-G91 -> 0 | N91: =(J91/G91)-100% -> #DIV/0!
C92: Servente de Canalizador | D92: h | F92: 12 | G92: =F92*E92 -> 0 | I92: =F92*$H$85 -> 17.4 | J92: =I92*E92 -> 0 | K92: =J92*1.23 -> 0 | M92: =J92-G92 -> 0 | N92: =(J92/G92)-100% -> #DIV/0!
C93: Montagem (loiças) | D93: un | F93: 20 | G93: =F93*E93 -> 0 | I93: =F93*$H$85 -> 29 | J93: =I93*E93 -> 0 | K93: =J93*1.23 -> 0 | M93: =J93-G93 -> 0 | N93: =(J93/G93)-100% -> #DIV/0!
C94: Trabalhos de movimentação e proteção de móveis | D94: un | F94: 20 | G94: =F94*E94 -> 0 | I94: =F94*$H$85 -> 29 | J94: =I94*E94 -> 0 | K94: =J94*1.23 -> 0 | M94: =J94-G94 -> 0 | N94: =(J94/G94)-100% -> #DIV/0!
C95: Trabalhos preparatórios de obra | D95: un | F95: 20 | G95: =F95*E95 -> 0 | I95: =F95*$H$85 -> 29 | J95: =I95*E95 -> 0 | K95: =J95*1.23 -> 0 | M95: =J95-G95 -> 0 | N95: =(J95/G95)-100% -> #DIV/0!
C96: Depósito de resíduos a vazadouro | D96: un | F96: 40 | G96: =F96*E96 -> 0 | I96: =F96*$H$85 -> 58 | J96: =I96*E96 -> 0 | K96: =J96*1.23 -> 0 | M96: =J96-G96 -> 0 | N96: =(J96/G96)-100% -> #DIV/0!
C97: Limpeza de obra | D97: un | F97: 20 | G97: =F97*E97 -> 0 | I97: =F97*$H$85 -> 29 | J97: =I97*E97 -> 0 | K97: =J97*1.23 -> 0 | M97: =J97-G97 -> 0 | N97: =(J97/G97)-100% -> #DIV/0!
C98: Deslocação | D98: un | F98: 20 | G98: =F98*E98 -> 0 | I98: =F98*$H$85 -> 29 | J98: =I98*E98 -> 0 | K98: =J98*1.23 -> 0 | M98: =J98-G98 -> 0 | N98: =(J98/G98)-100% -> #DIV/0!
C99: Total | G99: =SUM(G85:G94,G96:G98) -> 0 | I99: Total | J99: =SUM(J85:J98) -> 0 | K99: =SUM(K85:K98) -> 0 | M99: =SUM(M85:M98) -> 0
C100: Total/vg | E100: valor global | F100: 1 | G100: =ROUNDUP((G99/F100),0) -> 0
B102: ITEM | C102: DESCRIÇÃO | D102: UN | E102: QTD | F102: V.UN | G102: V.TOTAL | H102: K | I102: V.UN - Venda | J102: V.TOTAL - Venda | K102: IVA 23% | M102: Rentabilidade Estimada € | N102: Rentabilidade Estimada %
B104: Substituição de válvula de base de duche, incluindo todos os trabalhos necessários para excelente acabamento. | C104: Canalização | G104: =SUM(G105:G115) -> 0
C105: Desmontagem e montagem de base de duche | D105: un | F105: 150 | G105: =F105*E105 -> 0 | H105: 1.45 | I105: =F105*$H$85 -> 217.5 | J105: =I105*E105 -> 0 | K105: =J105*1.23 -> 0 | M105: =J105-G105 -> 0 | N105: =(J105/G105)-100% -> #DIV/0!
C106: Desmontagem e montagem de resguardo | D106: un | F106: 150 | G106: =F106*E106 -> 0 | I106: =F106*$H$85 -> 217.5 | J106: =I106*E106 -> 0 | K106: =J106*1.23 -> 0 | M106: =J106-G106 -> 0 | N106: =(J106/G106)-100% -> #DIV/0!
C107: Fornecimento e subsituição válvula base duche | D107: un | F107: 60 | G107: =F107*E107 -> 0 | I107: =F107*$H$85 -> 87 | J107: =I107*E107 -> 0 | K107: =J107*1.23 -> 0 | M107: =J107-G107 -> 0 | N107: =(J107/G107)-100% -> #DIV/0!
C108: Fornecimento e substituição de tubo Diâmetro 40" | D108: m2 | F108: 50 | G108: =F108*E108 -> 0 | I108: =F108*$H$85 -> 72.5 | J108: =I108*E108 -> 0 | K108: =J108*1.23 -> 0 | M108: =J108-G108 -> 0 | N108: =(J108/G108)-100% -> #DIV/0!
C109: Oficial de Canalizador | D109: h | F109: 17 | G109: =F109*E109 -> 0 | I109: =F109*$H$85 -> 24.65 | J109: =I109*E109 -> 0 | K109: =J109*1.23 -> 0 | M109: =J109-G109 -> 0 | N109: =(J109/G109)-100% -> #DIV/0!
C110: Servente de Canalizador | D110: h | F110: 12 | G110: =F110*E110 -> 0 | I110: =F110*$H$85 -> 17.4 | J110: =I110*E110 -> 0 | K110: =J110*1.23 -> 0 | M110: =J110-G110 -> 0 | N110: =(J110/G110)-100% -> #DIV/0!
...
